odoo10_addon_hr_employee_address_improved-10.0.1.0.0-py2.7-nspkg.pth
odoo/addons/hr_employee_address_improved/README.rst
odoo/addons/hr_employee_address_improved/__init__.py
odoo/addons/hr_employee_address_improved/__manifest__.py
odoo/addons/hr_employee_address_improved/hooks.py
odoo/addons/hr_employee_address_improved/static/description/icon.png
odoo/addons/hr_employee_address_improved/views/hr.xml
odoo10_addon_hr_employee_address_improved-10.0.1.0.0.dist-info/DESCRIPTION.rst
odoo10_addon_hr_employee_address_improved-10.0.1.0.0.dist-info/METADATA
odoo10_addon_hr_employee_address_improved-10.0.1.0.0.dist-info/RECORD
odoo10_addon_hr_employee_address_improved-10.0.1.0.0.dist-info/WHEEL
odoo10_addon_hr_employee_address_improved-10.0.1.0.0.dist-info/metadata.json
odoo10_addon_hr_employee_address_improved-10.0.1.0.0.dist-info/namespace_packages.txt
odoo10_addon_hr_employee_address_improved-10.0.1.0.0.dist-info/top_level.txt
